thds/termtool/__init__.py
thds/termtool/colorize.py
thds/termtool/py.typed
thds_termtool-1.0.20260130200322.dist-info/METADATA
thds_termtool-1.0.20260130200322.dist-info/WHEEL
thds_termtool-1.0.20260130200322.dist-info/top_level.txt
thds_termtool-1.0.20260130200322.dist-info/RECORD
