Metadata-Version: 2.4
Name: thds.termtool
Version: 1.0.20260130200322
Summary: Tools for terminal-based applications
Author-email: Trilliant Health <info@trillianthealth.com>
Project-URL: repository, https://github.com/TrilliantHealth/ds-monorepo
Requires-Python: >=3.9
Requires-Dist: ansicolors
Requires-Dist: thds-core
